abx_dl-1.0.5.dist-info/METADATA
abx_dl-1.0.5.dist-info/WHEEL
abx_dl-1.0.5.dist-info/entry_points.txt
abx_dl-1.0.5.dist-info/licenses/LICENSE
abx_dl/__init__.py
abx_dl/__main__.py
abx_dl/cli.py
abx_dl/config.py
abx_dl/dependencies.py
abx_dl/executor.py
abx_dl/models.py
abx_dl/package.json
abx_dl/plugins.py
abx_dl/process_utils.py
abx_dl-1.0.5.dist-info/RECORD
