Metadata-Version: 2.1
Name: abx-dl
Version: 1.0.5
Summary: All-in-one CLI tool to download and extract content from URLs
Keywords: scraping,crawling,downloading,internet archiving,web archiving,digipres,warc,preservation,backups,archiving,web,bookmarks,puppeteer,browser,download
Author-Email: Nick Sweeting <pyproject.toml@archivebox.io>
License: MIT
Classifier: Development Status :: 4 - Beta
Classifier: Environment :: Console
Classifier: Environment :: Web Environment
Classifier: Intended Audience :: Developers
Classifier: Intended Audience :: Education
Classifier: Intended Audience :: End Users/Desktop
Classifier: Intended Audience :: Information Technology
Classifier: Intended Audience :: Legal Industry
Classifier: Intended Audience :: System Administrators
Classifier: License :: OSI Approved :: MIT License
Classifier: Natural Language :: English
Classifier: Operating System :: OS Independent
Classifier: Programming Language :: Python :: 3
Classifier: Programming Language :: Python :: 3.10
Classifier: Programming Language :: Python :: 3.11
Classifier: Programming Language :: Python :: 3.12
Classifier: Topic :: Internet :: WWW/HTTP
Classifier: Topic :: Internet :: WWW/HTTP :: Indexing/Search
Classifier: Topic :: Internet :: WWW/HTTP :: WSGI :: Application
Classifier: Topic :: Sociology :: History
Classifier: Topic :: Software Development :: Libraries :: Python Modules
Classifier: Topic :: System :: Archiving
Classifier: Topic :: System :: Archiving :: Backup
Classifier: Topic :: System :: Recovery Tools
Classifier: Topic :: Utilities
Classifier: Typing :: Typed
Project-URL: Homepage, https://github.com/ArchiveBox/abx-dl
Project-URL: Source, https://github.com/ArchiveBox/abx-dl
Project-URL: Documentation, https://github.com/ArchiveBox/abx-dl
Project-URL: Bug Tracker, https://github.com/ArchiveBox/abx-dl/issues
Project-URL: Changelog, https://github.com/ArchiveBox/abx-dl/releases
Project-URL: Community, https://github.com/ArchiveBox/ArchiveBox/wiki/Web-Archiving-Community
Project-URL: Donate, https://github.com/ArchiveBox/ArchiveBox/wiki/Donations
Requires-Python: >=3.10
Requires-Dist: rich-click>=1.8.0
Requires-Dist: rich>=13.0.0
Requires-Dist: abx-pkg>=0.6.0
Requires-Dist: pydantic>=2.0.0
Requires-Dist: platformdirs>=4.0.0
Requires-Dist: requests>=2.28.0
Requires-Dist: psutil>=7.2.1
Provides-Extra: dev
Requires-Dist: pytest>=8.0.0; extra == "dev"
Requires-Dist: pytest-xdist>=3.5.0; extra == "dev"
Requires-Dist: ruff>=0.6.6; extra == "dev"
Requires-Dist: flake8>=7.1.1; extra == "dev"
Requires-Dist: mypy>=1.11.2; extra == "dev"
